rustbag-0.1.3.dist-info/METADATA
rustbag-0.1.3.dist-info/WHEEL
rustbag.libs/libbz2-c1f89286.so.1.0
rustbag/rustbag.pyi
rustbag/__init__.py
rustbag/rustbag.cpython-39-x86_64-linux-gnu.so
rustbag-0.1.3.dist-info/RECORD
