Metadata-Version: 2.1
Name: rustbag
Version: 0.1.3
Classifier: Development Status :: 3 - Alpha
Classifier: License :: OSI Approved :: MIT License
Classifier: Programming Language :: Rust
Classifier: Programming Language :: Python :: Implementation :: CPython
Classifier: Programming Language :: Python :: Implementation :: PyPy
Summary: ROSBag Reader focused on cloud storage access, written in Rust.
Author-email: Jakub Filipek <jfilipek@proton.me>
Requires-Python: >=3.8
Project-URL: Documentation, https://balbok0.github.io/rustbag/
Project-URL: Repository, https://github.com/balbok0/rustbag
Project-URL: Issues, https://github.com/balbok0/rustbag/issues
